CHANGELOG.txt
LICENCE.txt
MANIFEST.in
README.txt
setup.py
src/brinthan_psd.py
src/brinthan_psd.egg-info/PKG-INFO
src/brinthan_psd.egg-info/SOURCES.txt
src/brinthan_psd.egg-info/dependency_links.txt
src/brinthan_psd.egg-info/requires.txt
src/brinthan_psd.egg-info/top_level.txt