Metadata-Version: 2.1
Name: brinthan-psd
Version: 0.0.1.1
Summary: PSD calc
Home-page: 
Author: Brinthan K
Author-email: kanesalingambrinthan187@gmail.com
License: MIT
Keywords: DeepParticleSD,PSD,Deep Learning,Particle Size Distribution
Classifier: Development Status :: 5 - Production/Stable
Classifier: Intended Audience :: Education
Classifier: Operating System :: Microsoft :: Windows :: Windows 10
Classifier: License :: OSI Approved :: MIT License
Classifier: Programming Language :: Python :: 3
License-File: LICENCE.txt
